datasette_upload_csvs/__init__.py
datasette_upload_csvs/templates/upload_csv.html
datasette_upload_csvs/templates/upload_csv_done.html
datasette_upload_csvs-0.9.1.dist-info/LICENSE
datasette_upload_csvs-0.9.1.dist-info/METADATA
datasette_upload_csvs-0.9.1.dist-info/WHEEL
datasette_upload_csvs-0.9.1.dist-info/entry_points.txt
datasette_upload_csvs-0.9.1.dist-info/top_level.txt
datasette_upload_csvs-0.9.1.dist-info/RECORD
