Metadata-Version: 2.1
Name: datasette-upload-csvs
Version: 0.9.1
Summary: Datasette plugin for uploading CSV files and converting them to database tables
Home-page: https://datasette.io/plugins/datasette-upload-csvs
Author: Simon Willison
License: Apache License, Version 2.0
Project-URL: Issues, https://github.com/simonw/datasette-upload-csvs/issues
Project-URL: CI, https://github.com/simonw/datasette-upload-csvs/actions
Project-URL: Changelog, https://github.com/simonw/datasette-upload-csvs/releases
Requires-Python: >=3.7
License-File: LICENSE
Requires-Dist: datasette >=0.61
Requires-Dist: asgi-csrf >=0.7
Requires-Dist: starlette
Requires-Dist: aiofiles
Requires-Dist: python-multipart
Requires-Dist: charset-normalizer
Requires-Dist: sqlite-utils
Provides-Extra: test
Requires-Dist: pytest ; extra == 'test'
Requires-Dist: pytest-asyncio ; extra == 'test'
Requires-Dist: asgiref ; extra == 'test'
Requires-Dist: httpx ; extra == 'test'
Requires-Dist: asgi-lifespan ; extra == 'test'
